{
 "actions": [],
 "autoname": "naming_series:",
 "creation": "2021-02-17 09:20:24.655421",
 "doctype": "DocType",
 "editable_grid": 1,
 "engine": "InnoDB",
 "field_order": [
  "naming_series",
  "transport_template",
  "booking_date",
  "customer",
  "customer_ref_no",
  "scheduled_date",
  "column_break_5",
  "transport_job_type",
  "container_type",
  "container_no",
  "load_type",
  "vehicle_type",
  "hazardous",
  "refrigeration",
  "consolidate",
  "column_break_tjia",
  "transport_order",
  "status",
  "priority",
  "group_legs_in_one_runsheet",
  "section_break_jozr",
  "packages",
  "leg_plan_tab",
  "legs",
  "charges_tab",
  "charges",
  "entity_tab",
  "company",
  "branch",
  "profit_center",
  "cost_center",
  "column_break_xphe",
  "job_costing_number",
  "sustainability_tab",
  "sustainability_section",
  "total_distance",
  "fuel_consumption",
  "estimated_carbon_footprint",
  "column_break_sustainability",
  "sustainability_notes",
  "sla_tab",
  "sla_section",
  "sla_target_date",
  "sla_status",
  "column_break_sla",
  "sla_notes",
  "notes_tab",
  "notes_section",
  "internal_notes",
  "column_break_16",
  "client_notes",
  "connections_tab",
  "amended_from"
 ],
 "fields": [
  {
   "fieldname": "naming_series",
   "fieldtype": "Select",
   "label": "Naming Series",
   "options": "TRJ.#########"
  },
  {
   "default": "Normal",
   "fieldname": "priority",
   "fieldtype": "Select",
   "label": "Priority",
   "options": "Low\nNormal\nHigh"
  },
  {
   "fieldname": "customer",
   "fieldtype": "Link",
   "in_list_view": 1,
   "label": "Customer",
   "options": "Customer",
   "reqd": 1
  },
  {
   "fieldname": "booking_date",
   "fieldtype": "Date",
   "in_list_view": 1,
   "label": "Booking Date",
   "reqd": 1
  },
  {
   "fieldname": "customer_ref_no",
   "fieldtype": "Data",
   "in_list_view": 1,
   "label": "Customer Ref No"
  },
  {
   "fieldname": "column_break_5",
   "fieldtype": "Column Break"
  },
  {
   "fieldname": "vehicle_type",
   "fieldtype": "Link",
   "label": "Vehicle Type",
   "options": "Vehicle Type"
  },
  {
   "fieldname": "load_type",
   "fieldtype": "Link",
   "label": "Load Type",
   "link_filters": "[[\"Load Type\",\"transport\",\"=\",1]]",
   "options": "Load Type"
  },
  {
   "default": "0",
   "fieldname": "hazardous",
   "fieldtype": "Check",
   "label": "Hazardous"
  },
  {
   "default": "0",
   "fieldname": "refrigeration",
   "fieldtype": "Check",
   "in_list_view": 1,
   "label": "Refrigeration"
  },
  {
   "fieldname": "packages",
   "fieldtype": "Table",
   "label": "Packages",
   "options": "Transport Job Package"
  },
  {
   "collapsible": 1,
   "fieldname": "notes_section",
   "fieldtype": "Section Break",
   "label": "Notes"
  },
  {
   "fieldname": "internal_notes",
   "fieldtype": "Text Editor",
   "label": "Internal Notes"
  },
  {
   "fieldname": "column_break_16",
   "fieldtype": "Column Break"
  },
  {
   "fieldname": "client_notes",
   "fieldtype": "Text Editor",
   "label": "Client Notes"
  },
  {
   "fieldname": "column_break_tjia",
   "fieldtype": "Column Break"
  },
  {
   "fieldname": "charges_tab",
   "fieldtype": "Tab Break",
   "label": "Charges"
  },
  {
   "fieldname": "notes_tab",
   "fieldtype": "Tab Break",
   "label": "Notes"
  },
  {
   "fieldname": "charges",
   "fieldtype": "Table",
   "options": "Transport Job Charges"
  },
  {
   "fieldname": "sla_tab",
   "fieldtype": "Tab Break",
   "label": "Service Level"
  },
  {
   "collapsible": 1,
   "fieldname": "sla_section",
   "fieldtype": "Section Break",
   "label": "Service Level Agreement"
  },
  {
   "fieldname": "sla_target_date",
   "fieldtype": "Datetime",
   "label": "SLA Target Date"
  },
  {
   "default": "Not Applicable",
   "fieldname": "sla_status",
   "fieldtype": "Select",
   "label": "SLA Status",
   "options": "On Track\nAt Risk\nBreached\nNot Applicable"
  },
  {
   "fieldname": "column_break_sla",
   "fieldtype": "Column Break"
  },
  {
   "fieldname": "sla_notes",
   "fieldtype": "Text",
   "label": "SLA Notes"
  },
  {
   "fieldname": "section_break_jozr",
   "fieldtype": "Section Break"
  },
  {
   "fieldname": "transport_order",
   "fieldtype": "Link",
   "label": "Transport Order",
   "options": "Transport Order"
  },
  {
   "fieldname": "leg_plan_tab",
   "fieldtype": "Tab Break",
   "label": "Leg Plan"
  },
  {
   "fieldname": "transport_template",
   "fieldtype": "Link",
   "label": "Transport Template",
   "options": "Transport Template",
   "reqd": 1
  },
  {
   "fieldname": "legs",
   "fieldtype": "Table",
   "options": "Transport Job Legs"
  },
  {
   "fieldname": "container_type",
   "fieldtype": "Link",
   "hidden": 1,
   "label": "Container Type",
   "options": "Container Type"
  },
  {
   "fieldname": "container_no",
   "fieldtype": "Data",
   "hidden": 1,
   "label": "Container No."
  },
  {
   "fieldname": "entity_tab",
   "fieldtype": "Tab Break",
   "label": "Accounts"
  },
  {
   "fieldname": "company",
   "fieldtype": "Link",
   "label": "Company",
   "options": "Company",
   "reqd": 1
  },
  {
   "fieldname": "branch",
   "fieldtype": "Link",
   "label": "Branch",
   "options": "Branch",
   "reqd": 1
  },
  {
   "fieldname": "column_break_xphe",
   "fieldtype": "Column Break"
  },
  {
   "description": "This will be used when posting financial transactions to this job.",
   "fieldname": "job_costing_number",
   "fieldtype": "Link",
   "label": "Job Costing Number",
   "options": "Job Costing Number"
  },
  {
   "fieldname": "profit_center",
   "fieldtype": "Link",
   "label": "Profit Center",
   "options": "Profit Center",
   "reqd": 1
  },
  {
   "fieldname": "cost_center",
   "fieldtype": "Link",
   "label": "Cost Center",
   "link_filters": "[[\"Cost Center\",\"company\",\"=\",\"eval:doc.company\"]]",
   "options": "Cost Center",
   "reqd": 1
  },
  {
   "fieldname": "sustainability_tab",
   "fieldtype": "Tab Break",
   "label": "Sustainability"
  },
  {
   "fieldname": "sustainability_section",
   "fieldtype": "Section Break",
   "label": "Sustainability Metrics"
  },
  {
   "fieldname": "total_distance",
   "fieldtype": "Float",
   "label": "Total Distance (km)",
   "read_only": 1
  },
  {
   "fieldname": "fuel_consumption",
   "fieldtype": "Float",
   "label": "Estimated Fuel Consumption (L)",
   "read_only": 1
  },
  {
   "fieldname": "estimated_carbon_footprint",
   "fieldtype": "Float",
   "label": "Estimated Carbon Footprint (kg CO2e)",
   "read_only": 1
  },
  {
   "fieldname": "column_break_sustainability",
   "fieldtype": "Column Break"
  },
  {
   "fieldname": "sustainability_notes",
   "fieldtype": "Text",
   "label": "Sustainability Notes"
  },
  {
   "fieldname": "connections_tab",
   "fieldtype": "Tab Break",
   "label": "Connections",
   "show_dashboard": 1
  },
  {
   "fieldname": "amended_from",
   "fieldtype": "Link",
   "label": "Amended From",
   "no_copy": 1,
   "options": "Transport Job",
   "print_hide": 1,
   "read_only": 1,
   "search_index": 1
  },
  {
   "default": "Non-Container",
   "fieldname": "transport_job_type",
   "fieldtype": "Select",
   "label": "Transport Job Type",
   "options": "Container\nNon-Container\nSpecial\nOversized\nMultimodal\nHeavy Haul",
   "reqd": 1
  },
  {
   "default": "0",
   "fieldname": "consolidate",
   "fieldtype": "Check",
   "label": "Consolidate"
  },
  {
   "default": "0",
   "fieldname": "group_legs_in_one_runsheet",
   "fieldtype": "Check",
   "label": "Group Legs in One Runsheet"
  },
  {
   "fieldname": "scheduled_date",
   "fieldtype": "Date",
   "label": "Scheduled Date"
  },
  {
   "allow_on_submit": 1,
   "fieldname": "status",
   "fieldtype": "Select",
   "in_list_view": 1,
   "in_standard_filter": 1,
   "label": "Status",
   "options": "Draft\nSubmitted\nIn Progress\nCompleted\nCancelled",
   "reqd": 1
  }
 ],
 "is_submittable": 1,
 "links": [
  {
   "group": "Accounts",
   "link_doctype": "Sales Invoice",
   "link_fieldname": "job_costing_number"
  },
  {
   "group": "Accounts",
   "link_doctype": "Job Costing Number",
   "link_fieldname": "job_no"
  },
  {
   "group": "Operations",
   "link_doctype": "Transport Leg",
   "link_fieldname": "transport_job"
  }
 ],
 "modified": "2026-01-22 15:21:25.225753",
 "modified_by": "Administrator",
 "module": "Transport",
 "name": "Transport Job",
 "naming_rule": "By \"Naming Series\" field",
 "owner": "Administrator",
 "permissions": [
  {
   "create": 1,
   "delete": 1,
   "email": 1,
   "export": 1,
   "print": 1,
   "read": 1,
   "report": 1,
   "role": "System Manager",
   "share": 1,
   "submit": 1,
   "write": 1
  }
 ],
 "quick_entry": 1,
 "row_format": "Dynamic",
 "sort_field": "modified",
 "sort_order": "DESC",
 "states": [
  {
   "color": "Gray",
   "title": "Draft"
  },
  {
   "color": "Blue",
   "title": "Submitted"
  },
  {
   "color": "Orange",
   "title": "In Progress"
  },
  {
   "color": "Green",
   "title": "Completed"
  },
  {
   "color": "Red",
   "title": "Cancelled"
  }
 ],
 "track_changes": 1
}