{
 "actions": [],
 "allow_rename": 1,
 "autoname": "naming_series:",
 "creation": "2025-05-31 14:22:22.192721",
 "doctype": "DocType",
 "engine": "InnoDB",
 "field_order": [
  "milestones_tab",
  "milestone_html",
  "details_tab",
  "section_break_wacv",
  "transport_mode_column",
  "amended_from",
  "naming_series",
  "booking_date",
  "house_type",
  "direction",
  "column_break_lzrh",
  "airline",
  "local_customer",
  "freight_agent",
  "column_break_bpch",
  "release_type",
  "entry_type",
  "service_level",
  "section_break_cllp",
  "shipper",
  "origin_port",
  "etd",
  "column_break_oxhc",
  "consignee",
  "destination_port",
  "eta",
  "column_break_uvws",
  "volume",
  "weight",
  "chargeable",
  "packages_section",
  "packages",
  "insurance_section",
  "insurance_provider",
  "insurance_policy_number",
  "insurance_value",
  "column_break_insurance",
  "insurance_claim_number",
  "insurance_claim_status",
  "insurance_claim_date",
  "house_tab",
  "house_bl",
  "incoterm",
  "additional_terms",
  "column_break_mjzk",
  "packs",
  "inner",
  "gooda_value",
  "insurance",
  "section_break_olqg",
  "description",
  "column_break_ngoa",
  "marks_and_nos",
  "master_tab",
  "master_awb",
  "column_break_wwsh",
  "iata_section",
  "iata_status",
  "iata_message_id",
  "last_status_update",
  "column_break_iata",
  "house_awb_no",
  "booking_reference",
  "agent_reference",
  "dangerous_goods_tab",
  "contains_dangerous_goods",
  "dg_declaration_complete",
  "dg_compliance_status",
  "column_break_dg_main",
  "dg_emergency_contact",
  "dg_emergency_phone",
  "dg_emergency_email",
  "services_tab",
  "services",
  "charges_tab",
  "sales_quote",
  "charges",
  "contacts_and_addresses_tab",
  "shipper_address",
  "shipper_address_display",
  "column_break_cyzc",
  "consignee_address",
  "consignee_address_display",
  "section_break_haya",
  "shipper_contact",
  "shipper_contact_display",
  "column_break_tptt",
  "consignee_contact",
  "consignee_contact_display",
  "section_break_xuwf",
  "notify_party",
  "column_break_mzhi",
  "notify_party_address",
  "sustainability_tab",
  "sustainability_section",
  "estimated_carbon_footprint",
  "estimated_fuel_consumption",
  "column_break_sustainability",
  "sustainability_notes",
  "uld_tab",
  "uld_section",
  "uld_type",
  "uld_number",
  "uld_capacity_kg",
  "column_break_uld",
  "uld_position",
  "uld_tracking_status",
  "customs_tab",
  "customs_section",
  "customs_declaration_number",
  "customs_status",
  "customs_broker",
  "column_break_customs",
  "duty_amount",
  "tax_amount",
  "customs_clearance_date",
  "customs_notes",
  "temperature_tab",
  "temperature_section",
  "requires_temperature_control",
  "min_temperature",
  "max_temperature",
  "column_break_temperature",
  "temperature_monitoring",
  "cold_chain_compliance",
  "temperature_log",
  "documents_tab",
  "documents_section",
  "commercial_invoice_number",
  "packing_list_number",
  "certificate_of_origin",
  "column_break_documents",
  "export_license",
  "import_permit",
  "other_documents",
  "iata_advanced_tab",
  "casslink_section",
  "cass_participant_code",
  "cass_settlement_status",
  "cass_settlement_date",
  "column_break_cass",
  "cass_billing_reference",
  "cass_settlement_amount",
  "tact_section",
  "tact_rate_lookup",
  "tact_rate_reference",
  "tact_rate_amount",
  "column_break_tact",
  "tact_currency",
  "tact_rate_validity",
  "eawb_section",
  "eawb_enabled",
  "eawb_status",
  "eawb_digital_signature",
  "column_break_eawb",
  "eawb_signed_date",
  "eawb_signed_by",
  "tracking_tab",
  "tracking_section",
  "tracking_provider",
  "tracking_number",
  "tracking_url",
  "column_break_tracking",
  "real_time_tracking_enabled",
  "last_tracking_update",
  "tracking_status",
  "revenue_tab",
  "revenue_section",
  "revenue_recognition_date",
  "revenue_recognition_method",
  "revenue_amount",
  "column_break_revenue",
  "partial_revenue_enabled",
  "recognized_revenue_amount",
  "revenue_reversal_date",
  "billing_tab",
  "billing_section",
  "auto_billing_enabled",
  "billing_status",
  "sales_invoice",
  "column_break_billing",
  "billing_date",
  "billing_amount",
  "billing_currency",
  "connections_tab",
  "accounts_tab",
  "company",
  "branch",
  "cost_center",
  "profit_center",
  "job_costing_number"
 ],
 "fields": [
  {
   "fieldname": "section_break_wacv",
   "fieldtype": "Section Break"
  },
  {
   "fieldname": "amended_from",
   "fieldtype": "Link",
   "label": "Amended From",
   "no_copy": 1,
   "options": "Air Shipment",
   "print_hide": 1,
   "read_only": 1,
   "search_index": 1
  },
  {
   "fieldname": "naming_series",
   "fieldtype": "Select",
   "label": "Naming Series",
   "options": "AF.#########"
  },
  {
   "fieldname": "booking_date",
   "fieldtype": "Date",
   "in_list_view": 1,
   "label": "Booking Date",
   "reqd": 1
  },
  {
   "fieldname": "airline",
   "fieldtype": "Link",
   "label": "Airline",
   "options": "Airline"
  },
  {
   "fieldname": "column_break_lzrh",
   "fieldtype": "Column Break"
  },
  {
   "fieldname": "shipper",
   "fieldtype": "Link",
   "in_list_view": 1,
   "label": "Shipper",
   "options": "Shipper",
   "reqd": 1
  },
  {
   "fieldname": "consignee",
   "fieldtype": "Link",
   "label": "Consignee",
   "options": "Consignee",
   "reqd": 1
  },
  {
   "fieldname": "house_type",
   "fieldtype": "Select",
   "label": "House Type"
  },
  {
   "fieldname": "direction",
   "fieldtype": "Select",
   "in_list_view": 1,
   "label": "Direction",
   "options": "Import\nExport\nDomestic",
   "reqd": 1
  },
  {
   "fieldname": "local_customer",
   "fieldtype": "Link",
   "in_list_view": 1,
   "label": "Local Customer",
   "options": "Customer",
   "reqd": 1
  },
  {
   "fieldname": "freight_agent",
   "fieldtype": "Link",
   "label": "Freight Agent",
   "options": "Freight Agent"
  },
  {
   "fieldname": "column_break_bpch",
   "fieldtype": "Column Break"
  },
  {
   "fieldname": "release_type",
   "fieldtype": "Link",
   "label": "Release Type",
   "options": "Release Type"
  },
  {
   "fieldname": "entry_type",
   "fieldtype": "Select",
   "label": "Entry Type",
   "options": "Customs Permit\nTransshipment\nATA Carnet"
  },
  {
   "fieldname": "service_level",
   "fieldtype": "Link",
   "label": "Service Level",
   "options": "Service Level Agreement"
  },
  {
   "fieldname": "section_break_cllp",
   "fieldtype": "Section Break"
  },
  {
   "description": "Origin port UNLOCO code",
   "fieldname": "origin_port",
   "fieldtype": "Link",
   "label": "Origin Port",
   "options": "UNLOCO",
   "reqd": 1
  },
  {
   "fieldname": "column_break_oxhc",
   "fieldtype": "Column Break"
  },
  {
   "description": "Destination port UNLOCO code",
   "fieldname": "destination_port",
   "fieldtype": "Link",
   "label": "Destination Port",
   "options": "UNLOCO",
   "reqd": 1
  },
  {
   "fieldname": "column_break_uvws",
   "fieldtype": "Column Break"
  },
  {
   "fieldname": "etd",
   "fieldtype": "Date",
   "label": "ETD"
  },
  {
   "fieldname": "eta",
   "fieldtype": "Date",
   "label": "ETA"
  },
  {
   "fieldname": "volume",
   "fieldtype": "Float",
   "label": "Volume (cbm)"
  },
  {
   "fieldname": "weight",
   "fieldtype": "Float",
   "label": "Weight (kg)"
  },
  {
   "fieldname": "chargeable",
   "fieldtype": "Float",
   "label": "Chargeable (kg)"
  },
  {
   "fieldname": "dangerous_goods_tab",
   "fieldtype": "Tab Break",
   "label": "Dangerous Goods"
  },
  {
   "default": "0",
   "fieldname": "contains_dangerous_goods",
   "fieldtype": "Check",
   "label": "Contains Dangerous Goods"
  },
  {
   "default": "0",
   "fieldname": "dg_declaration_complete",
   "fieldtype": "Check",
   "label": "DG Declaration Complete"
  },
  {
   "fieldname": "dg_compliance_status",
   "fieldtype": "Select",
   "label": "DG Compliance Status",
   "options": "Compliant\nNon-Compliant\nUnder Review\nPending Documentation"
  },
  {
   "fieldname": "column_break_dg_main",
   "fieldtype": "Column Break"
  },
  {
   "fieldname": "dg_emergency_contact",
   "fieldtype": "Data",
   "label": "DG Emergency Contact"
  },
  {
   "fieldname": "dg_emergency_phone",
   "fieldtype": "Data",
   "label": "DG Emergency Phone"
  },
  {
   "fieldname": "dg_emergency_email",
   "fieldtype": "Data",
   "label": "DG Emergency Email"
  },
  {
   "fieldname": "house_tab",
   "fieldtype": "Tab Break",
   "label": "House"
  },
  {
   "fieldname": "house_bl",
   "fieldtype": "Data",
   "label": "House BL"
  },
  {
   "fieldname": "column_break_mjzk",
   "fieldtype": "Column Break"
  },
  {
   "fieldname": "incoterm",
   "fieldtype": "Link",
   "label": "Incoterm",
   "options": "Incoterm"
  },
  {
   "fieldname": "additional_terms",
   "fieldtype": "Data",
   "label": "Additional Terms"
  },
  {
   "fieldname": "packs",
   "fieldtype": "Float",
   "label": "Packs"
  },
  {
   "fieldname": "inner",
   "fieldtype": "Float",
   "label": "Inner"
  },
  {
   "fieldname": "gooda_value",
   "fieldtype": "Currency",
   "label": "Gooda Value"
  },
  {
   "fieldname": "insurance",
   "fieldtype": "Currency",
   "label": "Insurance"
  },
  {
   "fieldname": "section_break_olqg",
   "fieldtype": "Section Break"
  },
  {
   "fieldname": "description",
   "fieldtype": "Long Text",
   "label": "Description"
  },
  {
   "fieldname": "column_break_ngoa",
   "fieldtype": "Column Break"
  },
  {
   "fieldname": "marks_and_nos",
   "fieldtype": "Long Text",
   "label": "Marks and Nos"
  },
  {
   "fieldname": "master_tab",
   "fieldtype": "Tab Break",
   "label": "Master"
  },
  {
   "fieldname": "master_awb",
   "fieldtype": "Link",
   "label": "Master AWB",
   "options": "Master Air Waybill"
  },
  {
   "fieldname": "column_break_wwsh",
   "fieldtype": "Column Break"
  },
  {
   "collapsible": 1,
   "fieldname": "iata_section",
   "fieldtype": "Section Break",
   "label": "IATA Integration"
  },
  {
   "fieldname": "iata_status",
   "fieldtype": "Select",
   "label": "IATA Status",
   "options": "\nPending\nAccepted\nDeparted\nIn Transit\nArrived\nDelivered\nReady for Collection\nCustoms Cleared\nException"
  },
  {
   "fieldname": "iata_message_id",
   "fieldtype": "Data",
   "label": "IATA Message ID",
   "read_only": 1
  },
  {
   "fieldname": "last_status_update",
   "fieldtype": "Datetime",
   "label": "Last Status Update",
   "read_only": 1
  },
  {
   "fieldname": "column_break_iata",
   "fieldtype": "Column Break"
  },
  {
   "fieldname": "house_awb_no",
   "fieldtype": "Data",
   "label": "House AWB Number"
  },
  {
   "fieldname": "booking_reference",
   "fieldtype": "Data",
   "label": "Booking Reference"
  },
  {
   "fieldname": "agent_reference",
   "fieldtype": "Data",
   "label": "Agent Reference"
  },
  {
   "fieldname": "contacts_and_addresses_tab",
   "fieldtype": "Tab Break",
   "label": "Contacts & Addresses"
  },
  {
   "fieldname": "transport_mode_column",
   "fieldtype": "Column Break",
   "label": "Transport Mode",
   "options": "Air"
  },
  {
   "fieldname": "shipper_address",
   "fieldtype": "Link",
   "label": "Shipper Address",
   "options": "Address"
  },
  {
   "fieldname": "shipper_address_display",
   "fieldtype": "Small Text",
   "label": "Shipper Address Display"
  },
  {
   "fieldname": "column_break_cyzc",
   "fieldtype": "Column Break"
  },
  {
   "fieldname": "consignee_address",
   "fieldtype": "Link",
   "label": "Consignee Address",
   "options": "Address"
  },
  {
   "fieldname": "consignee_address_display",
   "fieldtype": "Small Text",
   "label": "Consignee Address Display"
  },
  {
   "fieldname": "notify_party",
   "fieldtype": "Data",
   "label": "Notify Party"
  },
  {
   "fieldname": "section_break_haya",
   "fieldtype": "Section Break"
  },
  {
   "fieldname": "shipper_contact",
   "fieldtype": "Link",
   "label": "Shipper Contact",
   "options": "Contact"
  },
  {
   "fieldname": "shipper_contact_display",
   "fieldtype": "Small Text",
   "label": "Shipper Contact Display"
  },
  {
   "fieldname": "column_break_tptt",
   "fieldtype": "Column Break"
  },
  {
   "fieldname": "consignee_contact",
   "fieldtype": "Link",
   "label": "Consignee Contact",
   "options": "Contact"
  },
  {
   "fieldname": "consignee_contact_display",
   "fieldtype": "Small Text",
   "label": "Consignee Contact Display"
  },
  {
   "fieldname": "section_break_xuwf",
   "fieldtype": "Section Break"
  },
  {
   "fieldname": "column_break_mzhi",
   "fieldtype": "Column Break"
  },
  {
   "fieldname": "notify_party_address",
   "fieldtype": "Small Text",
   "label": "Notify Party Address"
  },
  {
   "fieldname": "sustainability_tab",
   "fieldtype": "Tab Break",
   "label": "Sustainability"
  },
  {
   "fieldname": "sustainability_section",
   "fieldtype": "Section Break",
   "label": "Sustainability Metrics"
  },
  {
   "fieldname": "estimated_carbon_footprint",
   "fieldtype": "Float",
   "label": "Estimated Carbon Footprint (kg CO2e)",
   "read_only": 1
  },
  {
   "fieldname": "estimated_fuel_consumption",
   "fieldtype": "Float",
   "label": "Estimated Fuel Consumption (L)",
   "read_only": 1
  },
  {
   "fieldname": "column_break_sustainability",
   "fieldtype": "Column Break"
  },
  {
   "fieldname": "sustainability_notes",
   "fieldtype": "Text",
   "label": "Sustainability Notes"
  },
  {
   "fieldname": "uld_tab",
   "fieldtype": "Tab Break",
   "label": "ULD Management"
  },
  {
   "fieldname": "uld_section",
   "fieldtype": "Section Break",
   "label": "Unit Load Device (ULD) Information"
  },
  {
   "fieldname": "uld_type",
   "fieldtype": "Link",
   "label": "ULD Type",
   "options": "Unit Load Device"
  },
  {
   "description": "IATA ULD identification number",
   "fieldname": "uld_number",
   "fieldtype": "Data",
   "label": "ULD Number"
  },
  {
   "fieldname": "uld_capacity_kg",
   "fieldtype": "Float",
   "label": "ULD Capacity (kg)",
   "precision": "2",
   "read_only": 1
  },
  {
   "fieldname": "column_break_uld",
   "fieldtype": "Column Break"
  },
  {
   "description": "Position of ULD on aircraft (e.g., A1, B2)",
   "fieldname": "uld_position",
   "fieldtype": "Data",
   "label": "ULD Position"
  },
  {
   "fieldname": "uld_tracking_status",
   "fieldtype": "Select",
   "label": "ULD Tracking Status",
   "options": "\nNot Assigned\nAssigned\nLoaded\nIn Transit\nDelivered\nReturned"
  },
  {
   "fieldname": "customs_tab",
   "fieldtype": "Tab Break",
   "label": "Customs"
  },
  {
   "fieldname": "customs_section",
   "fieldtype": "Section Break",
   "label": "Customs Information"
  },
  {
   "fieldname": "customs_declaration_number",
   "fieldtype": "Data",
   "label": "Customs Declaration Number"
  },
  {
   "fieldname": "customs_status",
   "fieldtype": "Select",
   "label": "Customs Status",
   "options": "\nNot Submitted\nSubmitted\nUnder Review\nCleared\nHeld\nRejected"
  },
  {
   "fieldname": "customs_broker",
   "fieldtype": "Link",
   "label": "Customs Broker",
   "options": "Supplier"
  },
  {
   "fieldname": "column_break_customs",
   "fieldtype": "Column Break"
  },
  {
   "fieldname": "duty_amount",
   "fieldtype": "Currency",
   "label": "Duty Amount"
  },
  {
   "fieldname": "tax_amount",
   "fieldtype": "Currency",
   "label": "Tax Amount"
  },
  {
   "fieldname": "customs_clearance_date",
   "fieldtype": "Date",
   "label": "Customs Clearance Date"
  },
  {
   "fieldname": "customs_notes",
   "fieldtype": "Text",
   "label": "Customs Notes"
  },
  {
   "collapsible": 1,
   "fieldname": "insurance_section",
   "fieldtype": "Section Break",
   "label": "Cargo Insurance Information"
  },
  {
   "fieldname": "insurance_provider",
   "fieldtype": "Link",
   "label": "Insurance Provider",
   "options": "Supplier"
  },
  {
   "fieldname": "insurance_policy_number",
   "fieldtype": "Data",
   "label": "Insurance Policy Number"
  },
  {
   "description": "Insured value of the cargo",
   "fieldname": "insurance_value",
   "fieldtype": "Currency",
   "label": "Insurance Value"
  },
  {
   "fieldname": "column_break_insurance",
   "fieldtype": "Column Break"
  },
  {
   "fieldname": "insurance_claim_number",
   "fieldtype": "Data",
   "label": "Insurance Claim Number"
  },
  {
   "fieldname": "insurance_claim_status",
   "fieldtype": "Select",
   "label": "Claim Status",
   "options": "\nNo Claim\nClaim Filed\nUnder Review\nApproved\nRejected\nSettled"
  },
  {
   "fieldname": "insurance_claim_date",
   "fieldtype": "Date",
   "label": "Claim Date"
  },
  {
   "fieldname": "temperature_tab",
   "fieldtype": "Tab Break",
   "label": "Temperature Control"
  },
  {
   "fieldname": "temperature_section",
   "fieldtype": "Section Break",
   "label": "Temperature Control Information"
  },
  {
   "default": "0",
   "fieldname": "requires_temperature_control",
   "fieldtype": "Check",
   "label": "Requires Temperature Control"
  },
  {
   "depends_on": "eval:doc.requires_temperature_control==1",
   "fieldname": "min_temperature",
   "fieldtype": "Float",
   "label": "Minimum Temperature (\u00b0C)",
   "precision": "1"
  },
  {
   "depends_on": "eval:doc.requires_temperature_control==1",
   "fieldname": "max_temperature",
   "fieldtype": "Float",
   "label": "Maximum Temperature (\u00b0C)",
   "precision": "1"
  },
  {
   "fieldname": "column_break_temperature",
   "fieldtype": "Column Break"
  },
  {
   "default": "0",
   "depends_on": "eval:doc.requires_temperature_control==1",
   "fieldname": "temperature_monitoring",
   "fieldtype": "Check",
   "label": "Temperature Monitoring Enabled"
  },
  {
   "default": "0",
   "depends_on": "eval:doc.requires_temperature_control==1",
   "fieldname": "cold_chain_compliance",
   "fieldtype": "Check",
   "label": "Cold Chain Compliance Verified"
  },
  {
   "depends_on": "eval:doc.requires_temperature_control==1",
   "description": "Record of temperature readings during transit",
   "fieldname": "temperature_log",
   "fieldtype": "Long Text",
   "label": "Temperature Log"
  },
  {
   "fieldname": "documents_tab",
   "fieldtype": "Tab Break",
   "label": "Documents"
  },
  {
   "fieldname": "documents_section",
   "fieldtype": "Section Break",
   "label": "Document Management"
  },
  {
   "fieldname": "commercial_invoice_number",
   "fieldtype": "Data",
   "label": "Commercial Invoice Number"
  },
  {
   "fieldname": "packing_list_number",
   "fieldtype": "Data",
   "label": "Packing List Number"
  },
  {
   "fieldname": "certificate_of_origin",
   "fieldtype": "Data",
   "label": "Certificate of Origin"
  },
  {
   "fieldname": "column_break_documents",
   "fieldtype": "Column Break"
  },
  {
   "fieldname": "export_license",
   "fieldtype": "Data",
   "label": "Export License"
  },
  {
   "fieldname": "import_permit",
   "fieldtype": "Data",
   "label": "Import Permit"
  },
  {
   "description": "List of other required documents (e.g., health certificates, phytosanitary certificates)",
   "fieldname": "other_documents",
   "fieldtype": "Long Text",
   "label": "Other Documents"
  },
  {
   "fieldname": "sales_quote",
   "fieldtype": "Link",
   "label": "Sales Quote",
   "options": "Sales Quote"
  },
  {
   "fieldname": "charges",
   "fieldtype": "Table",
   "label": "Charges",
   "options": "Air Shipment Charges"
  },
  {
   "fieldname": "iata_advanced_tab",
   "fieldtype": "Tab Break",
   "label": "IATA Advanced"
  },
  {
   "collapsible": 1,
   "fieldname": "casslink_section",
   "fieldtype": "Section Break",
   "label": "CASSLink Integration"
  },
  {
   "description": "IATA CASS participant code for billing and settlement",
   "fieldname": "cass_participant_code",
   "fieldtype": "Data",
   "label": "CASS Participant Code"
  },
  {
   "fieldname": "cass_settlement_status",
   "fieldtype": "Select",
   "label": "CASS Settlement Status",
   "options": "\nPending\nSubmitted\nSettled\nDisputed\nRejected"
  },
  {
   "fieldname": "cass_settlement_date",
   "fieldtype": "Date",
   "label": "CASS Settlement Date"
  },
  {
   "fieldname": "column_break_cass",
   "fieldtype": "Column Break"
  },
  {
   "fieldname": "cass_billing_reference",
   "fieldtype": "Data",
   "label": "CASS Billing Reference"
  },
  {
   "fieldname": "cass_settlement_amount",
   "fieldtype": "Currency",
   "label": "CASS Settlement Amount"
  },
  {
   "collapsible": 1,
   "fieldname": "tact_section",
   "fieldtype": "Section Break",
   "label": "TACT Integration"
  },
  {
   "default": "0",
   "fieldname": "tact_rate_lookup",
   "fieldtype": "Check",
   "label": "Use TACT Rate Lookup"
  },
  {
   "description": "Reference number from TACT rate lookup",
   "fieldname": "tact_rate_reference",
   "fieldtype": "Data",
   "label": "TACT Rate Reference"
  },
  {
   "fieldname": "tact_rate_amount",
   "fieldtype": "Currency",
   "label": "TACT Rate Amount"
  },
  {
   "fieldname": "column_break_tact",
   "fieldtype": "Column Break"
  },
  {
   "fieldname": "tact_currency",
   "fieldtype": "Link",
   "label": "TACT Currency",
   "options": "Currency"
  },
  {
   "fieldname": "tact_rate_validity",
   "fieldtype": "Date",
   "label": "TACT Rate Validity Date"
  },
  {
   "collapsible": 1,
   "fieldname": "eawb_section",
   "fieldtype": "Section Break",
   "label": "e-AWB (Electronic Air Waybill)"
  },
  {
   "default": "0",
   "fieldname": "eawb_enabled",
   "fieldtype": "Check",
   "label": "e-AWB Enabled"
  },
  {
   "depends_on": "eval:doc.eawb_enabled==1",
   "fieldname": "eawb_status",
   "fieldtype": "Select",
   "label": "e-AWB Status",
   "options": "\nNot Created\nCreated\nSigned\nSubmitted\nAccepted\nRejected"
  },
  {
   "depends_on": "eval:doc.eawb_enabled==1",
   "fieldname": "eawb_digital_signature",
   "fieldtype": "Data",
   "label": "Digital Signature",
   "read_only": 1
  },
  {
   "fieldname": "column_break_eawb",
   "fieldtype": "Column Break"
  },
  {
   "depends_on": "eval:doc.eawb_enabled==1",
   "fieldname": "eawb_signed_date",
   "fieldtype": "Datetime",
   "label": "e-AWB Signed Date",
   "read_only": 1
  },
  {
   "depends_on": "eval:doc.eawb_enabled==1",
   "fieldname": "eawb_signed_by",
   "fieldtype": "Link",
   "label": "Signed By",
   "options": "User",
   "read_only": 1
  },
  {
   "fieldname": "tracking_tab",
   "fieldtype": "Tab Break",
   "label": "Tracking"
  },
  {
   "fieldname": "tracking_section",
   "fieldtype": "Section Break",
   "label": "Real-time Tracking"
  },
  {
   "fieldname": "tracking_provider",
   "fieldtype": "Select",
   "label": "Tracking Provider",
   "options": "\nIATA\nAirlines\nThird Party\nCustom"
  },
  {
   "fieldname": "tracking_number",
   "fieldtype": "Data",
   "label": "Tracking Number"
  },
  {
   "description": "URL for customer tracking portal",
   "fieldname": "tracking_url",
   "fieldtype": "Data",
   "label": "Tracking URL"
  },
  {
   "fieldname": "column_break_tracking",
   "fieldtype": "Column Break"
  },
  {
   "default": "0",
   "fieldname": "real_time_tracking_enabled",
   "fieldtype": "Check",
   "label": "Real-time Tracking Enabled"
  },
  {
   "fieldname": "last_tracking_update",
   "fieldtype": "Datetime",
   "label": "Last Tracking Update",
   "read_only": 1
  },
  {
   "fieldname": "tracking_status",
   "fieldtype": "Select",
   "label": "Tracking Status",
   "options": "\nPending\nIn Transit\nDelivered\nException",
   "read_only": 1
  },
  {
   "fieldname": "revenue_tab",
   "fieldtype": "Tab Break",
   "label": "Revenue"
  },
  {
   "fieldname": "revenue_section",
   "fieldtype": "Section Break",
   "label": "Revenue Recognition"
  },
  {
   "fieldname": "revenue_recognition_date",
   "fieldtype": "Date",
   "label": "Revenue Recognition Date"
  },
  {
   "fieldname": "revenue_recognition_method",
   "fieldtype": "Select",
   "label": "Recognition Method",
   "options": "\nOn Delivery\nOn Departure\nOn Booking\nPercentage Complete\nMilestone Based"
  },
  {
   "fieldname": "revenue_amount",
   "fieldtype": "Currency",
   "label": "Total Revenue Amount"
  },
  {
   "fieldname": "column_break_revenue",
   "fieldtype": "Column Break"
  },
  {
   "default": "0",
   "fieldname": "partial_revenue_enabled",
   "fieldtype": "Check",
   "label": "Partial Revenue Recognition"
  },
  {
   "fieldname": "recognized_revenue_amount",
   "fieldtype": "Currency",
   "label": "Recognized Revenue Amount",
   "read_only": 1
  },
  {
   "description": "Date when revenue was reversed (if applicable)",
   "fieldname": "revenue_reversal_date",
   "fieldtype": "Date",
   "label": "Revenue Reversal Date"
  },
  {
   "fieldname": "billing_tab",
   "fieldtype": "Tab Break",
   "label": "Billing"
  },
  {
   "fieldname": "billing_section",
   "fieldtype": "Section Break",
   "label": "Billing Automation"
  },
  {
   "default": "0",
   "fieldname": "auto_billing_enabled",
   "fieldtype": "Check",
   "label": "Auto Billing Enabled"
  },
  {
   "fieldname": "billing_status",
   "fieldtype": "Select",
   "label": "Billing Status",
   "options": "\nNot Billed\nPending\nBilled\nPartially Billed\nOverdue\nCancelled"
  },
  {
   "fieldname": "sales_invoice",
   "fieldtype": "Link",
   "label": "Sales Invoice",
   "options": "Sales Invoice"
  },
  {
   "fieldname": "column_break_billing",
   "fieldtype": "Column Break"
  },
  {
   "fieldname": "billing_date",
   "fieldtype": "Date",
   "label": "Billing Date"
  },
  {
   "fieldname": "billing_amount",
   "fieldtype": "Currency",
   "label": "Billing Amount"
  },
  {
   "fieldname": "billing_currency",
   "fieldtype": "Link",
   "label": "Billing Currency",
   "options": "Currency"
  },
  {
   "fieldname": "services_tab",
   "fieldtype": "Tab Break",
   "label": "Services"
  },
  {
   "fieldname": "charges_tab",
   "fieldtype": "Tab Break",
   "label": "Charges"
  },
  {
   "fieldname": "services",
   "fieldtype": "Table",
   "options": "Air Shipment Services"
  },
  {
   "fieldname": "connections_tab",
   "fieldtype": "Tab Break",
   "label": "Connections",
   "show_dashboard": 1
  },
  {
   "fieldname": "accounts_tab",
   "fieldtype": "Tab Break",
   "label": "Accounts"
  },
  {
   "fieldname": "company",
   "fieldtype": "Link",
   "label": "Company",
   "options": "Company",
   "reqd": 1
  },
  {
   "fieldname": "branch",
   "fieldtype": "Link",
   "label": "Branch",
   "options": "Branch",
   "reqd": 1
  },
  {
   "fieldname": "cost_center",
   "fieldtype": "Link",
   "label": "Cost Center",
   "link_filters": "[[\"Cost Center\",\"company\",\"=\",\"eval:doc.company\"]]",
   "options": "Cost Center",
   "reqd": 1
  },
  {
   "fieldname": "profit_center",
   "fieldtype": "Link",
   "label": "Profit Center",
   "options": "Profit Center",
   "reqd": 1
  },
  {
   "description": "This will be used when posting financial transactions to this job.",
   "fieldname": "job_costing_number",
   "fieldtype": "Link",
   "label": "Job Costing Number",
   "options": "Job Costing Number"
  },
  {
   "fieldname": "packages",
   "fieldtype": "Table",
   "options": "Air Shipment Packages"
  },
  {
   "fieldname": "milestones_tab",
   "fieldtype": "Tab Break",
   "label": "Dashboard"
  },
  {
   "fieldname": "milestone_html",
   "fieldtype": "HTML",
   "is_virtual": 1
  },
  {
   "fieldname": "details_tab",
   "fieldtype": "Tab Break",
   "label": "Details"
  },
  {
   "collapsible": 1,
   "fieldname": "packages_section",
   "fieldtype": "Section Break",
   "label": "Packages"
  }
 ],
 "grid_page_length": 50,
 "index_web_pages_for_search": 1,
 "is_submittable": 1,
 "links": [],
 "modified": "2025-12-12 11:55:02.888196",
 "modified_by": "Administrator",
 "module": "Air Freight",
 "name": "Air Shipment",
 "naming_rule": "By \"Naming Series\" field",
 "owner": "Administrator",
 "permissions": [
  {
   "create": 1,
   "delete": 1,
   "email": 1,
   "export": 1,
   "print": 1,
   "read": 1,
   "report": 1,
   "role": "System Manager",
   "share": 1,
   "submit": 1,
   "write": 1
  }
 ],
 "row_format": "Dynamic",
 "sort_field": "modified",
 "sort_order": "DESC",
 "states": []
}